async_unittest/__init__.py
async_unittest/case.py
async_unittest/mock.py
async_unittest-0.0.1.dist-info/DESCRIPTION.rst
async_unittest-0.0.1.dist-info/METADATA
async_unittest-0.0.1.dist-info/RECORD
async_unittest-0.0.1.dist-info/WHEEL
async_unittest-0.0.1.dist-info/metadata.json
async_unittest-0.0.1.dist-info/top_level.txt
async_unittest-0.0.1.dist-info/zip-safe
