Metadata-Version: 2.0
Name: async-unittest
Version: 0.0.1
Summary: Make unittest can test asynio libraries
Home-page: https://github.com/AuTa/async_unittest/
Author: AuTa King
Author-email: auta520@live.com
License: UNKNOWN
Keywords: unittest,test,testing,asyncio,async,mock
Platform: UNKNOWN
Classifier: Development Status :: 1 - Planning
Classifier: Framework :: AsyncIO
Classifier: Intended Audience :: Developers
Classifier: Topic :: Software Development :: Testing
Classifier: License :: OSI Approved :: BSD License
Classifier: Programming Language :: Python :: 3.6
Requires-Python: >=3.6
